MANIFEST.in
README
__init__.py
__pkginfo__.py
ccplugin.py
geoutils.py
hooks.py
setup.py
site_cubicweb.py
sobjects.py
vocabularies.py
cubicweb_datacat.egg-info/PKG-INFO
cubicweb_datacat.egg-info/SOURCES.txt
cubicweb_datacat.egg-info/dependency_links.txt
cubicweb_datacat.egg-info/not-zip-safe
cubicweb_datacat.egg-info/requires.txt
cubicweb_datacat.egg-info/top_level.txt
data/cubes.datacat.js
data/leaflet.draw.css
data/leaflet.draw.js
data/od_licenses.json
entities/__init__.py
entities/geo.py
i18n/de.po
i18n/en.po
i18n/es.po
i18n/fr.po
migration/0.1.1_Any.py
migration/0.1.4_Any.py
migration/0.10.0_Any.py
migration/0.14.0_Any.py
migration/0.2.0_Any.py
migration/0.3.0_Any.py
migration/0.4.0_Any.py
migration/0.5.0_Any.py
migration/0.6.0_Any.py
migration/0.6.1_Any.py
migration/0.7.0_Any.py
migration/0.7.1_Any.py
migration/0.8.0_Any.py
migration/0.8.2_Any.py
migration/0.8.5_Any.py
migration/0.9.0_Any.py
migration/0.9.0_Any.py.orig
migration/postcreate.py
migration/data/application.csv
migration/data/audio.csv
migration/data/image.csv
migration/data/message.csv
migration/data/model.csv
migration/data/multipart.csv
migration/data/text.csv
migration/data/video.csv
schema/__init__.py
schema/geo.py
test/__init__.py
test/test_datacat.py
test/test_geoutils.py
test/unittest_entities.py
test/unittest_entities_geo.py
test/unittest_hooks.py
test/unittest_schema.py
test/unittest_sobjects.py
test/unittest_views.py
test/unittest_views_geo.py
test/unittest_vocabularies.py
test/utils.py
views/__init__.py
views/geo.py
views/geo.py.orig
views/urlrewrite.py