Metadata-Version: 1.1
Name: cubicweb-datacat
Version: 0.14.0
Summary: Data catalog
Home-page: http://www.cubicweb.org/project/cubicweb-datacat
Author: LOGILAB S.A. (Paris, FRANCE)
Author-email: contact@logilab.fr
License: LGPL
Platform: UNKNOWN
Classifier: Environment :: Web Environment
Classifier: Framework :: CubicWeb
Classifier: Programming Language :: Python
Classifier: Programming Language :: JavaScript
